awespykit/__info__.py
awespykit/__init__.py
awespykit/__main__.py
awespykit/runpykit.py
awespykit/com/__init__.py
awespykit/com/common.py
awespykit/com/enums.py
awespykit/com/mapping.py
awespykit/com/requires.py
awespykit/com/widgets.py
awespykit/logic/__init__.py
awespykit/logic/about_window.py
awespykit/logic/cloud_function.py
awespykit/logic/generic_output.py
awespykit/logic/indexurl_manager.py
awespykit/logic/messagebox.py
awespykit/logic/package_download.py
awespykit/logic/package_manager.py
awespykit/logic/pyinstaller_tool.py
awespykit/logic/query_file_path.py
awespykit/res/__init__.py
awespykit/res/res.py
awespykit/settings/__init__.py
awespykit/settings/abstract_config.py
awespykit/settings/cloud_function.py
awespykit/settings/indexurl_manager.py
awespykit/settings/main_entrance.py
awespykit/settings/package_download.py
awespykit/settings/package_manager.py
awespykit/settings/pyinstaller_tool.py
awespykit/ui/__init__.py
awespykit/ui/about_window.py
awespykit/ui/addenv_dialog.py
awespykit/ui/cloud_excludes.py
awespykit/ui/cloud_function.py
awespykit/ui/environ_chosen.py
awespykit/ui/generic_output.py
awespykit/ui/imports_check.py
awespykit/ui/index_manager.py
awespykit/ui/main_entrance.py
awespykit/ui/package_download.py
awespykit/ui/package_install.py
awespykit/ui/package_manager.py
awespykit/ui/pyinstaller_tool.py
awespykit/ui/query_panel.py
awespykit/ui/show_download.py
awespykit/utils/__init__.py
awespykit/utils/cip.py
awespykit/utils/main.py
awespykit/utils/pyi.py
awespykit/utils/thmt.py
awespykit/utils/venv.py
Awespykit-2.1.0.dist-info/LICENSE
Awespykit-2.1.0.dist-info/METADATA
Awespykit-2.1.0.dist-info/WHEEL
Awespykit-2.1.0.dist-info/entry_points.txt
Awespykit-2.1.0.dist-info/top_level.txt
Awespykit-2.1.0.dist-info/RECORD
