Metadata-Version: 2.1
Name: Awespykit
Version: 2.1.0
Summary: 关于Python的GUI工具箱：包管理、程序打包、切换Pip源、分发包下载、云函数打包
Author-email: hrp <pphrp@qq.com>, hrpzcf <pphrp@qq.com>
License: GPLv3
Platform: win32
Platform: win_amd64
Classifier: Intended Audience :: Developers
Classifier: Development Status :: 4 - Beta
Classifier: License :: OSI Approved :: GNU General Public License v3 (GPLv3)
Classifier: Programming Language :: Python :: 3.7
Classifier: Programming Language :: Python :: 3.8
Classifier: Programming Language :: Python :: 3.9
Classifier: Programming Language :: Python :: 3.10
Classifier: Environment :: Win32 (MS Windows)
Classifier: Operating System :: Microsoft :: Windows :: Windows 7
Classifier: Operating System :: Microsoft :: Windows :: Windows 10
Classifier: Operating System :: Microsoft :: Windows :: Windows 11
Requires-Python: >=3.7
License-File: LICENSE
Requires-Dist: PyQt5 (>=5.15.2)
Requires-Dist: pywin32 (>=224)
Requires-Dist: fastpip (<2.0,>=1.7)
Requires-Dist: chardet (>=4.0.0)
Requires-Dist: importlib-metadata (>=6.1.0) ; python_version < "3.8"
